util_logger/__init__.py
util_logger/logger.py
util_logger-0.3.1.dist-info/LICENSE.txt
util_logger-0.3.1.dist-info/METADATA
util_logger-0.3.1.dist-info/WHEEL
util_logger-0.3.1.dist-info/entry_points.txt
util_logger-0.3.1.dist-info/RECORD
