Metadata-Version: 2.1
Name: util-logger
Version: 0.3.1
Summary: Wrapper package to the logging std module
Author: tomtenuta
Author-email: tom@tenuta.io
Requires-Python: >=3.10,<4.0
Classifier: Programming Language :: Python :: 3
Classifier: Programming Language :: Python :: 3.10
Classifier: Programming Language :: Python :: 3.11
